[
  {
    "key": "configuration",
    "path": "configuration.yaml",
    "file": "configuration.json",
    "tsFile": "configuration.ts",
    "fromType": "ConfigurationRoot"
  },
  {
    "key": "integration-homeassistant-packages",
    "path": "configuration.yaml/homeassistant/packages",
    "file": "integration-homeassistant-packages.json",
    "tsFile": "configuration.ts",
    "fromType": "ConfigurationRoot"
  },
  {
    "key": "integration-homeassistant-customize",
    "path": "configuration.yaml/homeassistant/customize",
    "file": "integration-homeassistant-customize.json",
    "tsFile": "./integrations/core/homeassistant.ts",
    "fromType": "CoreCustomize"
  },
  {
    "key": "integration-scene",
    "path": "configuration.yaml/scene",
    "file": "integration-scene.json",
    "tsFile": "integrations/core/scene.ts",
    "fromType": "File"
  },
  {
    "key": "integration-http",
    "path": "configuration.yaml/http",
    "file": "integration-http.json",
    "tsFile": "integrations/core/http.ts",
    "fromType": "Schema"
  },
  {
    "key": "integration-input_boolean",
    "path": "configuration.yaml/input_boolean",
    "file": "integration-input_boolean.json",
    "tsFile": "integrations/core/input_boolean.ts",
    "fromType": "File"
  },
  {
    "key": "integration-input_button",
    "path": "configuration.yaml/input_button",
    "file": "integration-input_button.json",
    "tsFile": "integrations/core/input_button.ts",
    "fromType": "File"
  },
  {
    "key": "integration-input_datetime",
    "path": "configuration.yaml/input_datetime",
    "file": "integration-input_datetime.json",
    "tsFile": "integrations/core/input_datetime.ts",
    "fromType": "File"
  },
  {
    "key": "integration-input_number",
    "path": "configuration.yaml/input_number",
    "file": "integration-input_number.json",
    "tsFile": "integrations/core/input_number.ts",
    "fromType": "File"
  },
  {
    "key": "integration-input_select",
    "path": "configuration.yaml/input_select",
    "file": "integration-input_select.json",
    "tsFile": "integrations/core/input_select.ts",
    "fromType": "File"
  },
  {
    "key": "integration-input_text",
    "path": "configuration.yaml/input_text",
    "file": "integration-input_text.json",
    "tsFile": "integrations/core/input_text.ts",
    "fromType": "File"
  },
  {
    "key": "integration-script",
    "path": "configuration.yaml/script",
    "file": "integration-script.json",
    "tsFile": "integrations/core/script.ts",
    "fromType": "File"
  },
  {
    "key": "integration-sensor",
    "path": "configuration.yaml/sensor",
    "file": "integration-sensor.json",
    "tsFile": "integrations/core/sensor.ts",
    "fromType": "File"
  },
  {
    "key": "integration-template",
    "path": "configuration.yaml/template",
    "file": "integration-template.json",
    "tsFile": "integrations/core/template.ts",
    "fromType": "TemplateFile"
  },
  {
    "key": "integration-alarm_control_panel",
    "path": "configuration.yaml/alarm_control_panel",
    "file": "integration-alarm_control_panel.json",
    "tsFile": "integrations/core/alarm_control_panel.ts",
    "fromType": "File"
  },
  {
    "key": "integration-automation",
    "path": "configuration.yaml/automation",
    "file": "integration-automation.json",
    "tsFile": "integrations/core/automation.ts",
    "fromType": "File"
  },
  {
    "key": "integration-binary_sensor",
    "path": "configuration.yaml/binary_sensor",
    "file": "integration-binary_sensor.json",
    "tsFile": "integrations/core/binary_sensor.ts",
    "fromType": "File"
  },
  {
    "key": "integration-camera",
    "path": "configuration.yaml/camera",
    "file": "integration-camera.json",
    "tsFile": "integrations/core/camera.ts",
    "fromType": "File"
  },
  {
    "key": "integration-climate",
    "path": "configuration.yaml/climate",
    "file": "integration-climate.json",
    "tsFile": "integrations/core/climate.ts",
    "fromType": "File"
  },
  {
    "key": "integration-cover",
    "path": "configuration.yaml/cover",
    "file": "integration-cover.json",
    "tsFile": "integrations/core/cover.ts",
    "fromType": "File"
  },
  {
    "key": "integration-device_tracker",
    "path": "configuration.yaml/device_tracker",
    "file": "integration-device_tracker.json",
    "tsFile": "integrations/core/device_tracker.ts",
    "fromType": "File"
  },
  {
    "key": "integration-fan",
    "path": "configuration.yaml/fan",
    "file": "integration-fan.json",
    "tsFile": "integrations/core/fan.ts",
    "fromType": "File"
  },
  {
    "key": "integration-light",
    "path": "configuration.yaml/light",
    "file": "integration-light.json",
    "tsFile": "integrations/core/light.ts",
    "fromType": "File"
  },
  {
    "key": "integration-lock",
    "path": "configuration.yaml/lock",
    "file": "integration-lock.json",
    "tsFile": "integrations/core/lock.ts",
    "fromType": "File"
  },
  {
    "key": "integration-number",
    "path": "configuration.yaml/number",
    "file": "integration-number.json",
    "tsFile": "integrations/core/number.ts",
    "fromType": "File"
  },
  {
    "key": "integration-select",
    "path": "configuration.yaml/select",
    "file": "integration-select.json",
    "tsFile": "integrations/core/select.ts",
    "fromType": "File"
  },
  {
    "key": "integration-switch",
    "path": "configuration.yaml/switch",
    "file": "integration-switch.json",
    "tsFile": "integrations/core/switch.ts",
    "fromType": "File"
  },
  {
    "key": "integration-vacuum",
    "path": "configuration.yaml/vacuum",
    "file": "integration-vacuum.json",
    "tsFile": "integrations/core/vacuum.ts",
    "fromType": "File"
  },
  {
    "key": "integration-weather",
    "path": "configuration.yaml/weather",
    "file": "integration-weather.json",
    "tsFile": "integrations/core/weather.ts",
    "fromType": "File"
  },
  {
    "key": "lovelace-dashboard",
    "path": "ui-lovelace.yaml",
    "file": "lovelace-dashboard.json",
    "tsFile": "lovelace/dashboard.ts",
    "fromType": "Dashboard"
  },
  {
    "key": "lovelace-views",
    "path": "ui-lovelace.yaml/views",
    "file": "lovelace-views.json",
    "tsFile": "lovelace/view.ts",
    "fromType": "View"
  },
  {
    "key": "lovelace-cards",
    "path": "ui-lovelace.yaml/views/cards",
    "file": "lovelace-cards.json",
    "tsFile": "lovelace/types.ts",
    "fromType": "CardsFile"
  },
  {
    "key": "blueprint-automation",
    "path": "blueprints/automation",
    "file": "blueprint-automation.json",
    "tsFile": "integrations/core/blueprint.ts",
    "fromType": "AutomationBlueprint"
  },
  {
    "key": "blueprint-script",
    "path": "blueprints/script",
    "file": "blueprint-script.json",
    "tsFile": "integrations/core/blueprint.ts",
    "fromType": "ScriptBlueprint"
  },
  {
    "key": "custom-sentences",
    "path": "custom_sentences.yaml",
    "file": "custom-sentences.json",
    "tsFile": "integrations/core/conversation.ts",
    "fromType": "CustomSentence"
  }
]
